{
  "AWSTemplateFormatVersion": "2010-09-09",
  "Description": "The AWS CloudFormation template for this Serverless application",
  "Resources": {
    "CreateBookingLogGroup": {
      "Type": "AWS::Logs::LogGroup",
      "Properties": {
        "LogGroupName": "/aws/lambda/booking-service-dev-createBooking"
      }
    },
    "IamRoleLambdaExecution": {
      "Type": "AWS::IAM::Role",
      "Properties": {
        "AssumeRolePolicyDocument": {
          "Version": "2012-10-17",
          "Statement": [
            {
              "Effect": "Allow",
              "Principal": {
                "Service": [
                  "lambda.amazonaws.com"
                ]
              },
              "Action": [
                "sts:AssumeRole"
              ]
            }
          ]
        },
        "Policies": [
          {
            "PolicyName": {
              "Fn::Join": [
                "-",
                [
                  "booking-service",
                  "dev",
                  "lambda"
                ]
              ]
            },
            "PolicyDocument": {
              "Version": "2012-10-17",
              "Statement": [
                {
                  "Effect": "Allow",
                  "Action": [
                    "logs:CreateLogStream",
                    "logs:CreateLogGroup",
                    "logs:TagResource"
                  ],
                  "Resource": [
                    {
                      "Fn::Sub": "arn:${AWS::Partition}:logs:${AWS::Region}:${AWS::AccountId}:log-group:/aws/lambda/booking-service-dev*:*"
                    }
                  ]
                },
                {
                  "Effect": "Allow",
                  "Action": [
                    "logs:PutLogEvents"
                  ],
                  "Resource": [
                    {
                      "Fn::Sub": "arn:${AWS::Partition}:logs:${AWS::Region}:${AWS::AccountId}:log-group:/aws/lambda/booking-service-dev*:*:*"
                    }
                  ]
                },
                {
                  "Effect": "Allow",
                  "Action": [
                    "ssm:GetParameter",
                    "ssm:GetParameters"
                  ],
                  "Resource": [
                    {
                      "Fn::Sub": "arn:aws:ssm:${AWS::Region}:${AWS::AccountId}:parameter/FirebaseSDK"
                    }
                  ]
                },
                {
                  "Effect": "Allow",
                  "Action": [
                    "dynamodb:GetItem",
                    "dynamodb:PutItem",
                    "dynamodb:UpdateItem",
                    "dynamodb:DeleteItem",
                    "dynamodb:Query",
                    "dynamodb:Scan"
                  ],
                  "Resource": [
                    {
                      "Fn::Sub": "arn:aws:dynamodb:${AWS::Region}:${AWS::AccountId}:table/IdempotencyTable"
                    },
                    {
                      "Fn::Sub": "arn:aws:dynamodb:${AWS::Region}:${AWS::AccountId}:table/BookingsTable"
                    },
                    {
                      "Fn::Sub": "arn:aws:dynamodb:${AWS::Region}:${AWS::AccountId}:table/BookingsTable/index/*"
                    }
                  ]
                }
              ]
            }
          }
        ],
        "Path": "/",
        "RoleName": {
          "Fn::Join": [
            "-",
            [
              "booking-service",
              "dev",
              {
                "Ref": "AWS::Region"
              },
              "lambdaRole"
            ]
          ]
        }
      }
    },
    "CreateBookingLambdaFunction": {
      "Type": "AWS::Lambda::Function",
      "Properties": {
        "Code": {
          "S3Bucket": "serverless-framework-deployments-ap-south-1-cb00259d-5c2e",
          "S3Key": "serverless/booking-service/dev/1757496460707-2025-09-10T09:27:40.707Z/createBooking.zip"
        },
        "Handler": "src/handlers/createBookingHandler.handler",
        "Runtime": "nodejs18.x",
        "FunctionName": "booking-service-dev-createBooking",
        "MemorySize": 1024,
        "Timeout": 6,
        "Environment": {
          "Variables": {
            "DATABASE_URL": "postgresql://backendapp:backend123@salonapp.cheme8w42ux8.ap-south-1.rds.amazonaws.com/salondb",
            "FIREBASE_SECRET_NAME": "FirebaseSDK",
            "FIREBASE_WEB_API_KEY": "/firebase/firebase-web/api/key",
            "CUSTOM_AWS_REGION": "ap-south-1",
            "DYNAMODB_BOOKINGS_TABLE": "BookingsTable"
          }
        },
        "Role": {
          "Fn::GetAtt": [
            "IamRoleLambdaExecution",
            "Arn"
          ]
        }
      },
      "DependsOn": [
        "CreateBookingLogGroup"
      ]
    },
    "CreateBookingLambdaVersioneXZpLXcEupITAqDplIk7NnQT9UlANdN1lL8ECOi738": {
      "Type": "AWS::Lambda::Version",
      "DeletionPolicy": "Retain",
      "Properties": {
        "FunctionName": {
          "Ref": "CreateBookingLambdaFunction"
        },
        "CodeSha256": "vOCUIEk3+RyHPw2upCILYs7A4oBhjtST9xoHmKFTs4U="
      }
    },
    "CreateBookingLambdaPermissionHttpApi": {
      "Type": "AWS::Lambda::Permission",
      "Properties": {
        "FunctionName": {
          "Fn::GetAtt": [
            "CreateBookingLambdaFunction",
            "Arn"
          ]
        },
        "Action": "lambda:InvokeFunction",
        "Principal": "apigateway.amazonaws.com",
        "SourceArn": {
          "Fn::Join": [
            "",
            [
              "arn:",
              {
                "Ref": "AWS::Partition"
              },
              ":execute-api:",
              {
                "Ref": "AWS::Region"
              },
              ":",
              {
                "Ref": "AWS::AccountId"
              },
              ":",
              "fxh1zg6455",
              "/*"
            ]
          ]
        }
      }
    },
    "HttpApiIntegrationCreateBooking": {
      "Type": "AWS::ApiGatewayV2::Integration",
      "Properties": {
        "ApiId": "fxh1zg6455",
        "IntegrationType": "AWS_PROXY",
        "IntegrationUri": {
          "Fn::GetAtt": [
            "CreateBookingLambdaFunction",
            "Arn"
          ]
        },
        "PayloadFormatVersion": "2.0",
        "TimeoutInMillis": 30000
      }
    },
    "HttpApiRoutePostBookings": {
      "Type": "AWS::ApiGatewayV2::Route",
      "Properties": {
        "ApiId": "fxh1zg6455",
        "RouteKey": "POST /bookings",
        "Target": {
          "Fn::Join": [
            "/",
            [
              "integrations",
              {
                "Ref": "HttpApiIntegrationCreateBooking"
              }
            ]
          ]
        }
      },
      "DependsOn": "HttpApiIntegrationCreateBooking"
    },
    "BookingsTable": {
      "Type": "AWS::DynamoDB::Table",
      "Properties": {
        "TableName": "BookingsTable",
        "BillingMode": "PAY_PER_REQUEST",
        "AttributeDefinitions": [
          {
            "AttributeName": "id",
            "AttributeType": "S"
          },
          {
            "AttributeName": "locationId",
            "AttributeType": "S"
          },
          {
            "AttributeName": "startTime",
            "AttributeType": "S"
          }
        ],
        "KeySchema": [
          {
            "AttributeName": "id",
            "KeyType": "HASH"
          }
        ],
        "GlobalSecondaryIndexes": [
          {
            "IndexName": "LocationTimeIndex",
            "KeySchema": [
              {
                "AttributeName": "locationId",
                "KeyType": "HASH"
              },
              {
                "AttributeName": "startTime",
                "KeyType": "RANGE"
              }
            ],
            "Projection": {
              "ProjectionType": "ALL"
            }
          }
        ],
        "StreamSpecification": {
          "StreamViewType": "NEW_AND_OLD_IMAGES"
        }
      }
    }
  },
  "Outputs": {
    "ServerlessDeploymentBucketName": {
      "Value": "serverless-framework-deployments-ap-south-1-cb00259d-5c2e",
      "Export": {
        "Name": "sls-booking-service-dev-ServerlessDeploymentBucketName"
      }
    },
    "CreateBookingLambdaFunctionQualifiedArn": {
      "Description": "Current Lambda function version",
      "Value": {
        "Ref": "CreateBookingLambdaVersioneXZpLXcEupITAqDplIk7NnQT9UlANdN1lL8ECOi738"
      },
      "Export": {
        "Name": "sls-booking-service-dev-CreateBookingLambdaFunctionQualifiedArn"
      }
    }
  }
}